kitchenware_model_package/.DS_Store
kitchenware_model_package/VERSION
kitchenware_model_package/__init__.py
kitchenware_model_package/config/__init__.py
kitchenware_model_package/config/core.py
kitchenware_model_package/config.yml
kitchenware_model_package/data_processing/__init__.py
kitchenware_model_package/data_processing/data_manager.py
kitchenware_model_package/data_processing/preprocessor.py
kitchenware_model_package/datasets/.DS_Store
kitchenware_model_package/datasets/__init__.py
kitchenware_model_package/datasets/kitchenware-data/.DS_Store
kitchenware_model_package/datasets/kitchenware-data/images/.DS_Store
kitchenware_model_package/datasets/kitchenware-data/images/0000.jpg
kitchenware_model_package/datasets/kitchenware-data/images/0001.jpg
kitchenware_model_package/datasets/kitchenware-data/images/0002.jpg
kitchenware_model_package/datasets/kitchenware-data/images/0004.jpg
kitchenware_model_package/datasets/kitchenware-data/images/0009.jpg
kitchenware_model_package/datasets/kitchenware-data/images/0013.jpg
kitchenware_model_package/datasets/kitchenware-data/images/0020.jpg
kitchenware_model_package/datasets/kitchenware-data/images/0024.jpg
kitchenware_model_package/datasets/kitchenware-data/images/0026.jpg
kitchenware_model_package/datasets/kitchenware-data/images/0192.jpg
kitchenware_model_package/datasets/kitchenware-data/images/0199.jpg
kitchenware_model_package/datasets/kitchenware-data/images/0207.jpg
kitchenware_model_package/datasets/kitchenware-data/images/0291.jpg
kitchenware_model_package/datasets/kitchenware-data/images/0299.jpg
kitchenware_model_package/datasets/kitchenware-data/images/0385.jpg
kitchenware_model_package/datasets/kitchenware-data/images/0403.jpg
kitchenware_model_package/datasets/kitchenware-data/images/0412.jpg
kitchenware_model_package/datasets/kitchenware-data/images/0422.jpg
kitchenware_model_package/datasets/kitchenware-data/test.csv
kitchenware_model_package/datasets/kitchenware-data/train.csv
kitchenware_model_package-0.0.4.dist-info/METADATA
kitchenware_model_package-0.0.4.dist-info/WHEEL
kitchenware_model_package-0.0.4.dist-info/RECORD
